<?xml version="1.0" encoding="UTF-8"?>
<downloads>
  <template>
  <download>
    <prod></prod>
    <vers></vers>
    <des></des>
    <url></url>
    <cat></cat>
    <os></os>
    <sze></sze>
  </download>
  </template>

  <download>
    <prod>AuCloud</prod>
    <vers>2017.6.11</vers>
    <des>Aurawin cloud synchronization app</des>
    <url>/downloads/Internal/AuCloud-2017.6.11-linux-x64.zip</url>
    <cat>Desktop</cat>
    <os>Linux 64bit</os>
    <sze>2.9 MB</sze>
  </download>
  <download>
    <prod>AuCloud</prod>
    <vers>2017.12.5</vers>
    <des>Aurawin cloud synchronization app</des>
    <url>/downloads/Internal/AuCloud-2017.12.5-windows-x64.exe</url>
    <cat>Desktop</cat>
    <os>Windows 64bit</os>
    <sze>4.7 MB</sze>
  </download>
  <download>
    <prod>AuCloud</prod>
    <vers>2017.12.5</vers>
    <des>Aurawin cloud synchronization app</des>
    <url>/downloads/Internal/AuCloud-2017.12.5-windows-32.exe</url>
    <cat>Desktop</cat>
    <os>Windows 32bit</os>
    <sze>3.3 MB</sze>
  </download>
  <download>
    <prod>AuConsole</prod>
    <vers>2017.6.11</vers>
    <des>Aurawin Social Computing Server GUI Console</des>
    <url>/downloads/Internal/AuConsole-2017.6.11-linux-x64.zip</url>
    <cat>Server</cat>
    <os>Linux 64bit</os>
    <sze>3.9 MB</sze>
  </download>
  <download>
    <prod>AuSCS</prod>
    <vers>2017.6.11</vers>
    <des>Aurawin Social Computing Server</des>
    <url>/downloads/Internal/AuSCS-2017.6.11-linux-x64.zip</url>
    <cat>Server</cat>
    <os>Linux 64bit</os>
    <sze>7.8 MB</sze>
  </download>
  <download>
    <prod>AuVDM</prod>
    <vers>2017.6.11</vers>
    <des>Aurawin Virtual Desktop Machine (VDM)</des>
    <url>/Downloads/Internal/AuVDM-2017.6.11.zip</url>
    <cat>Server</cat>
    <os>Aurawin</os>
    <sze>36.8 MB</sze>
  </download>
</downloads>
